ConformationalAnalysis.py
clustering.py
elements.py
mGenerate_PyMOL_Session.py
mGenerate_conf_analysis.py
main.py
pca.py
pca_creation.py
pymol.py
xyz.py
omolab_conf_analysis-0.1.11.data/scripts/mGenerate_PyMOL_Session.py
omolab_conf_analysis-0.1.11.data/scripts/mGenerate_PyMOL_Session.sh
omolab_conf_analysis-0.1.11.data/scripts/mGenerate_conf_analysis.py
omolab_conf_analysis-0.1.11.data/scripts/mGenerate_conf_analysis.sh
omolab_conf_analysis-0.1.11.dist-info/METADATA
omolab_conf_analysis-0.1.11.dist-info/WHEEL
omolab_conf_analysis-0.1.11.dist-info/top_level.txt
omolab_conf_analysis-0.1.11.dist-info/RECORD
